Metadata-Version: 2.1
Name: Inline-input
Version: 0.7
Summary: Rethinking input() with inline auto-completion, minimum character requirement, and more.
Author: NeuralTeam
Author-email: NeuralTeam@mail.ru
License: UNKNOWN
Platform: UNKNOWN
Classifier: Operating System :: Microsoft :: Windows
Classifier: Programming Language :: Python
